orderedYAML/__init__.py
orderedYAML/core.py
orderedYAML/tests/__init__.py
orderedYAML/tests/test_orderedYAML.py
orderedyaml-0.1.2.dist-info/METADATA
orderedyaml-0.1.2.dist-info/WHEEL
orderedyaml-0.1.2.dist-info/licenses/LICENSE
orderedyaml-0.1.2.dist-info/RECORD
