Metadata-Version: 2.4
Name: orderedYAML
Version: 0.1.2
Summary: Order nested YAML output using ruamel.yaml with custom key ordering
Author-email: Sam Griffith <samgriffith3@gmail.com>
License: MIT
License-File: LICENSE
Keywords: commentedmap,ordered,ruamel,yaml
Requires-Python: >=3.7
Requires-Dist: ruamel-yaml>=0.17.0
